eink_template_gen/__init__.py
eink_template_gen/__main__.py
eink_template_gen/actions.py
eink_template_gen/config.py
eink_template_gen/corners.py
eink_template_gen/cover_drawing.py
eink_template_gen/cover_elements.py
eink_template_gen/covers.py
eink_template_gen/devices.json
eink_template_gen/devices.py
eink_template_gen/drawing.py
eink_template_gen/lsystem.py
eink_template_gen/noise.py
eink_template_gen/separator_config.py
eink_template_gen/separators.py
eink_template_gen/templates.py
eink_template_gen/utils.py
eink_template_gen/wizard.py
eink_template_gen-0.5.1.dist-info/licenses/LICENSE
eink_template_gen-0.5.1.dist-info/METADATA
eink_template_gen-0.5.1.dist-info/WHEEL
eink_template_gen-0.5.1.dist-info/entry_points.txt
eink_template_gen-0.5.1.dist-info/top_level.txt
eink_template_gen-0.5.1.dist-info/RECORD
