Metadata-Version: 2.4
Name: eink-template-gen
Version: 0.5.1
Summary: Pixel-perfect template generator for e-ink devices like Supernote, reMarkable, and Boox
Author-email: Caleb Christensen <git@calebc42.com>
License: GPL-3.0-or-later
Project-URL: Homepage, https://github.com/calebc42/eink-template-gen
Project-URL: Repository, https://github.com/calebc42/eink-template-gen
Project-URL: Issues, https://github.com/calebc42/eink-template-gen/issues
Project-URL: Documentation, https://github.com/calebc42/eink-template-gen#readme
Keywords: supernote,e-ink,templates,pdf,remarkable,boox,eink,notebook
Classifier: Development Status :: 4 - Beta
Classifier: Intended Audience :: End Users/Desktop
Classifier: License :: OSI Approved :: GNU General Public License v3 or later (GPLv3+)
Classifier: Programming Language :: Python :: 3
Classifier: Programming Language :: Python :: 3.8
Classifier: Programming Language :: Python :: 3.9
Classifier: Programming Language :: Python :: 3.10
Classifier: Programming Language :: Python :: 3.11
Classifier: Programming Language :: Python :: 3.12
Classifier: Topic :: Multimedia :: Graphics
Classifier: Topic :: Printing
Classifier: Operating System :: OS Independent
Requires-Python: >=3.8
License-File: LICENSE
Requires-Dist: pycairo>=1.20.0
Requires-Dist: platformdirs
Requires-Dist: importlib-resources; python_version < "3.9"
Provides-Extra: dev
Requires-Dist: pytest>=7.0.0; extra == "dev"
Requires-Dist: pytest-cov>=3.0.0; extra == "dev"
Requires-Dist: black>=22.0.0; extra == "dev"
Requires-Dist: ruff>=0.1.0; extra == "dev"
Provides-Extra: test
Requires-Dist: pytest>=7.0.0; extra == "test"
Requires-Dist: pytest-cov>=3.0.0; extra == "test"
Requires-Dist: psutil>=5.9.0; extra == "test"
Requires-Dist: pillow>=9.0.0; extra == "test"
Requires-Dist: numpy>=1.21.0; extra == "test"
Dynamic: license-file
